ddex_parser-0.4.5.dist-info/METADATA
ddex_parser-0.4.5.dist-info/WHEEL
ddex_parser-0.4.5.dist-info/entry_points.txt
ddex_parser/__init__.py
ddex_parser/_internal.abi3.so
ddex_parser/cli.py
ddex_parser-0.4.5.dist-info/RECORD
