Metadata-Version: 2.4
Name: ddex-parser
Version: 0.4.5
Classifier: Development Status :: 3 - Alpha
Classifier: Intended Audience :: Developers
Classifier: License :: OSI Approved :: MIT License
Classifier: Programming Language :: Python :: 3
Classifier: Programming Language :: Python :: 3.8
Classifier: Programming Language :: Python :: 3.9
Classifier: Programming Language :: Python :: 3.10
Classifier: Programming Language :: Python :: 3.11
Classifier: Programming Language :: Python :: 3.12
Classifier: Programming Language :: Rust
Classifier: Topic :: Software Development :: Libraries :: Python Modules
Classifier: Topic :: Multimedia :: Sound/Audio
Requires-Dist: pytest>=7.0 ; extra == 'dev'
Requires-Dist: pytest-asyncio>=0.21 ; extra == 'dev'
Requires-Dist: pytest-benchmark>=4.0 ; extra == 'dev'
Requires-Dist: black>=23.0 ; extra == 'dev'
Requires-Dist: mypy>=1.0 ; extra == 'dev'
Requires-Dist: ruff>=0.1 ; extra == 'dev'
Requires-Dist: pandas>=1.5 ; extra == 'pandas'
Requires-Dist: pyarrow>=10.0 ; extra == 'pandas'
Provides-Extra: dev
Provides-Extra: pandas
Summary: High-performance DDEX XML parser for Python
Keywords: ddex,xml,parser,music,metadata,ern
Author-email: Kevin Marques Moo <daddykev@gmail.com>
License: MIT
Requires-Python: >=3.8
